{
    "inflation": {
        "Western and Central Africa": {
            "value": "4.7",
            "date": "30 June 2023"
        },
        "Sub-Saharan Africa (UN)": {
            "value": "5.6",
            "date": "30 June 2023"
        },
        "Southern Africa": {
            "value": "5.3",
            "date": "30 June 2023"
        },
        "Africa": {
            "value": "5.8",
            "date": "30 June 2023"
        },
        "Middle Africa": {
            "value": "7.7",
            "date": "30 June 2023"
        },
        "Eastern and Southern Africa": {
            "value": "6.6",
            "date": "30 June 2023"
        },
        "Sub-Saharan Africa (WB)": {
            "value": "5.6",
            "date": "30 June 2023"
        },
        "Western Africa": {
            "value": "5.1",
            "date": "30 June 2023"
        },
        "North Africa (WB)": {
            "value": "9.2",
            "date": "30 June 2023"
        },
        "Northern Africa": {
            "value": "9.2",
            "date": "30 June 2023"
        },
        "Eastern Africa": {
            "value": "7.4",
            "date": "30 June 2023"
        }
    },
    "gdp_growth": {
        "North Africa (WB)": {
            "value": "3.0%",
            "year": "2023"
        },
        "Sub-Saharan Africa (WB)": {
            "value": "4.1%",
            "year": "2023"
        },
        "Africa": {
            "value": "4.0%",
            "year": "2023"
        },
        "Sub-Saharan Africa (UN)": {
            "value": "4.1%",
            "year": "2023"
        },
        "Eastern and Southern Africa": {
            "value": "3.6%",
            "year": "2023"
        },
        "Western and Central Africa": {
            "value": "4.4%",
            "year": "2023"
        },
        "Northern Africa": {
            "value": "2.8%",
            "year": "2023"
        },
        "Middle Africa": {
            "value": "3.5%",
            "year": "2023"
        },
        "Western Africa": {
            "value": "4.9%",
            "year": "2023"
        },
        "Southern Africa": {
            "value": "2.8%",
            "year": "2023"
        },
        "Eastern Africa": {
            "value": "4.1%",
            "year": "2023"
        }
    },
    "insufficient_food": {
        "North Africa (WB)": {
            "value": "39,686,703",
            "date": "07 September"
        },
        "Sub-Saharan Africa (WB)": {
            "value": "363,371,778",
            "date": "07 September"
        },
        "Africa": {
            "value": "403,058,481",
            "date": "07 September"
        },
        "Sub-Saharan Africa (UN)": {
            "value": "346,986,638",
            "date": "07 September"
        },
        "Eastern and Southern Africa": {
            "value": "171,612,850",
            "date": "07 September"
        },
        "Western and Central Africa": {
            "value": "191,475,070",
            "date": "07 September"
        },
        "Northern Africa": {
            "value": "56,071,843",
            "date": "07 September"
        },
        "Middle Africa": {
            "value": "69,510,960",
            "date": "07 September"
        },
        "Western Africa": {
            "value": "169,126,453",
            "date": "07 September"
        },
        "Southern Africa": {
            "value": "1,726,125",
            "date": "07 September"
        },
        "Eastern Africa": {
            "value": "106,623,100",
            "date": "07 September"
        }
    }
}