{
    "inflation": {
        "Sub-Saharan Africa (WB)": {
            "value": "5.2",
            "date": "31 July 2023"
        },
        "Western Africa": {
            "value": "5.2",
            "date": "31 July 2023"
        },
        "Southern Africa": {
            "value": "4.5",
            "date": "31 July 2023"
        },
        "Sub-Saharan Africa (UN)": {
            "value": "5.2",
            "date": "31 July 2023"
        },
        "Africa": {
            "value": "5.4",
            "date": "31 July 2023"
        },
        "Middle Africa": {
            "value": "4.2",
            "date": "31 July 2023"
        },
        "Eastern and Southern Africa": {
            "value": "5.8",
            "date": "31 July 2023"
        },
        "Western and Central Africa": {
            "value": "4.6",
            "date": "31 July 2023"
        },
        "North Africa (WB)": {
            "value": "9.1",
            "date": "31 July 2023"
        },
        "Northern Africa": {
            "value": "9.1",
            "date": "31 July 2023"
        },
        "Eastern Africa": {
            "value": "6.6",
            "date": "31 July 2023"
        }
    },
    "gdp_growth": {
        "North Africa (WB)": {
            "value": "3.0%",
            "year": "2023"
        },
        "Sub-Saharan Africa (WB)": {
            "value": "4.1%",
            "year": "2023"
        },
        "Africa": {
            "value": "4.0%",
            "year": "2023"
        },
        "Sub-Saharan Africa (UN)": {
            "value": "4.1%",
            "year": "2023"
        },
        "Eastern and Southern Africa": {
            "value": "3.6%",
            "year": "2023"
        },
        "Western and Central Africa": {
            "value": "4.4%",
            "year": "2023"
        },
        "Northern Africa": {
            "value": "2.8%",
            "year": "2023"
        },
        "Middle Africa": {
            "value": "3.5%",
            "year": "2023"
        },
        "Western Africa": {
            "value": "4.9%",
            "year": "2023"
        },
        "Southern Africa": {
            "value": "2.8%",
            "year": "2023"
        },
        "Eastern Africa": {
            "value": "4.1%",
            "year": "2023"
        }
    },
    "insufficient_food": {
        "North Africa (WB)": {
            "value": "39,112,396",
            "date": "16 October"
        },
        "Sub-Saharan Africa (WB)": {
            "value": "368,733,040",
            "date": "16 October"
        },
        "Africa": {
            "value": "407,845,436",
            "date": "16 October"
        },
        "Sub-Saharan Africa (UN)": {
            "value": "352,657,608",
            "date": "16 October"
        },
        "Eastern and Southern Africa": {
            "value": "173,923,279",
            "date": "16 October"
        },
        "Western and Central Africa": {
            "value": "194,531,394",
            "date": "16 October"
        },
        "Northern Africa": {
            "value": "55,187,828",
            "date": "16 October"
        },
        "Middle Africa": {
            "value": "70,466,313",
            "date": "16 October"
        },
        "Western Africa": {
            "value": "171,417,943",
            "date": "16 October"
        },
        "Southern Africa": {
            "value": "1,767,515",
            "date": "16 October"
        },
        "Eastern Africa": {
            "value": "109,005,837",
            "date": "16 October"
        }
    }
}