{
    "inflation": {
        "Western and Central Africa": {
            "value": "4.7",
            "date": "31 August 2023"
        },
        "Sub-Saharan Africa (UN)": {
            "value": "5.1",
            "date": "31 August 2023"
        },
        "Southern Africa": {
            "value": "4.7",
            "date": "31 August 2023"
        },
        "Africa": {
            "value": "5.2",
            "date": "31 August 2023"
        },
        "Middle Africa": {
            "value": "4.7",
            "date": "31 August 2023"
        },
        "Eastern and Southern Africa": {
            "value": "5.8",
            "date": "31 August 2023"
        },
        "Sub-Saharan Africa (WB)": {
            "value": "5.1",
            "date": "31 August 2023"
        },
        "Western Africa": {
            "value": "4.8",
            "date": "31 August 2023"
        },
        "North Africa (WB)": {
            "value": "9.4",
            "date": "31 August 2023"
        },
        "Northern Africa": {
            "value": "9.4",
            "date": "31 August 2023"
        },
        "Eastern Africa": {
            "value": "6.7",
            "date": "31 August 2023"
        }
    },
    "gdp_growth": {
        "North Africa (WB)": {
            "value": "3.8%",
            "year": "2023"
        },
        "Sub-Saharan Africa (WB)": {
            "value": "4.1%",
            "year": "2023"
        },
        "Africa": {
            "value": "4.1%",
            "year": "2023"
        },
        "Sub-Saharan Africa (UN)": {
            "value": "4.1%",
            "year": "2023"
        },
        "Eastern and Southern Africa": {
            "value": "3.8%",
            "year": "2023"
        },
        "Western and Central Africa": {
            "value": "4.4%",
            "year": "2023"
        },
        "Northern Africa": {
            "value": "4.0%",
            "year": "2023"
        },
        "Middle Africa": {
            "value": "4.0%",
            "year": "2023"
        },
        "Western Africa": {
            "value": "4.5%",
            "year": "2023"
        },
        "Southern Africa": {
            "value": "2.8%",
            "year": "2023"
        },
        "Eastern Africa": {
            "value": "4.2%",
            "year": "2023"
        }
    },
    "insufficient_food": {
        "North Africa (WB)": {
            "value": "40,067,493",
            "date": "14 November"
        },
        "Sub-Saharan Africa (WB)": {
            "value": "368,378,247",
            "date": "14 November"
        },
        "Africa": {
            "value": "408,445,740",
            "date": "14 November"
        },
        "Sub-Saharan Africa (UN)": {
            "value": "352,305,608",
            "date": "14 November"
        },
        "Eastern and Southern Africa": {
            "value": "173,417,784",
            "date": "14 November"
        },
        "Western and Central Africa": {
            "value": "194,681,428",
            "date": "14 November"
        },
        "Northern Africa": {
            "value": "56,140,132",
            "date": "14 November"
        },
        "Middle Africa": {
            "value": "69,455,958",
            "date": "14 November"
        },
        "Western Africa": {
            "value": "172,719,096",
            "date": "14 November"
        },
        "Southern Africa": {
            "value": "1,706,693",
            "date": "14 November"
        },
        "Eastern Africa": {
            "value": "108,423,861",
            "date": "14 November"
        }
    }
}